setup.py
namedmaps/__init__.py
namedmaps/editmap.py
namedmaps/namededitmap.py
namedmaps/namedmap.py
namedmaps/utils.py
namedmaps.egg-info/PKG-INFO
namedmaps.egg-info/SOURCES.txt
namedmaps.egg-info/dependency_links.txt
namedmaps.egg-info/top_level.txt