Metadata-Version: 1.0
Name: namedmaps
Version: 0.1.0
Summary: Python dictionaries with items also accessible via dot-notation
Home-page: https://github.com/pcattori/namedmaps
Author: Pedro Cattori
Author-email: pcattori@gmail.com
License: MIT
Platform: UNKNOWN
